{"query": {"url": "https://www.car.gr/20823246-honda-freeway-250", "type": "CAR_ADDE", "trial_count": 1, "last_processed": 1553102860}, "title": "Honda Freeway 250  '98", "ad_id": "20823246", "ad_data": {"Make/Model": "Honda Freeway 250 '98", "Classified number": "20823246", "Price": "€750", "Category": "Bike - Roller/Scooter", "Registration": "2 / 1998", "Mileage": "76,500 km", "Fuel type": "Gasoline", "Cubic capacity": "250 cc", "Power": "21 bhp", "Color": "Grey", "Previous owners": "1", "Modified": "35 days", "Times clicked": "125", "Short link": "www.car.gr/20823246", "Telephone": "None"}, "ad_seller": {}, "metadata": {"type": "Bikes", "brand": "Honda", "model": "Freeway 250"}, "extras": ["Antique-Classic", "Cargo Rack", "Centerstand", "Four-stroke engine", "Kick-Starter", "Service Book", "Sidestand", "Καρμπυρατέρ"], "description": "Σε άριστη κατάσταση με τα σέρβις στην ώρα του.Καταλληλο για μέσα στην πόλη,πόλη οικονομικό. - Less - "}