{"query": {"url": "https://www.car.gr/17884083-honda-crf-450", "type": "CAR_ADDE", "trial_count": 1, "last_processed": 1553095551}, "title": "Honda CRF 450  '15", "ad_id": "17884083", "ad_data": {"Make/Model": "Honda CRF 450 '15", "Classified number": "17884083", "Price": "€4.300", "Category": "Bike - Motocross", "Registration": "1 / 2015", "Fuel type": "Gasoline", "Cubic capacity": "450 cc", "Power": "55 bhp", "Color": "Red", "Modified": "3 days", "Times clicked": "1307", "Short link": "www.car.gr/17884083", "Telephone": "None"}, "ad_seller": {}, "metadata": {"type": "Bikes", "brand": "Honda", "model": "CRF 450"}, "extras": ["Exchange with Moto accepted"], "description": "Ανταλλαγη με motocross - Less - "}