{"query": {"url": "https://www.car.gr/19998783-yamaha-x-max-400", "type": "CAR_ADDE", "trial_count": 1, "last_processed": 1553094037}, "title": "Yamaha X-MAX 400  '16", "ad_id": "19998783", "ad_data": {"Make/Model": "Yamaha X-MAX 400 '16", "Classified number": "19998783", "Price": "€4.590", "Category": "Bike - Roller/Scooter", "Registration": "9 / 2016", "Mileage": "26,900 km", "Fuel type": "Gasoline", "Cubic capacity": "400 cc", "Power": "34 bhp", "Color": "Grey", "Previous owners": "1", "Modified": "18 hours", "Times clicked": "1812", "Short link": "www.car.gr/19998783", "Telephone": "+30 2107776004"}, "ad_seller": {"Dealer": "EUROMOTO", "Address": "ΚΑΛΛΙΡPΟΗΣ35", "City": "ΑΘΗΝΑ", "": "+30 2107772005", "Fax": "+30 2107772488", "Dealer page": "https//tsm-euromoto.car.gr/", "Website": "http//www.euromoto.gr"}, "metadata": {"type": "Bikes", "brand": "Yamaha", "model": "X-MAX 400"}, "extras": ["ABS", "Alarm", "Automatic", "Cast wheels", "Centerstand", "Electric starter", "Four-stroke engine", "Gelatin", "Greek Dealership", "Injection", "Kick-Starter", "Service Book", "Sidestand", "Trip computer"], "description": ""}