{"query": {"url": "https://www.car.gr/8563760-piaggio-beverly-500", "type": "CAR_ADDE", "trial_count": 1, "last_processed": 1553100214}, "title": "Piaggio Beverly 500  '04", "ad_id": "8563760", "ad_data": {"Make/Model": "Piaggio Beverly 500 '04", "Classified number": "8563760", "Price": "€1.400", "Category": "Bike - Roller/Scooter", "Registration": "8 / 2004", "Mileage": "45,000 km", "Fuel type": "Gasoline", "Cubic capacity": "459 cc", "Power": "500 bhp", "Color": "Bordeaux (Metallic)", "Kteo to": "12 / 2017", "Modified": "16 days", "Times clicked": "4405", "Short link": "www.car.gr/8563760", "Telephone": "None"}, "ad_seller": {}, "metadata": {"type": "Bikes", "brand": "Piaggio", "model": "Beverly 500"}, "extras": [], "description": ""}