{"query": {"url": "https://www.car.gr/21160805-piaggio-beverly-350-sporttouring", "type": "CAR_ADDE", "trial_count": 1, "last_processed": 1553100093}, "title": "Piaggio Beverly 350 SportTouring  '12", "ad_id": "21160805", "ad_data": {"Make/Model": "Piaggio Beverly 350 SportTouring '12", "Classified number": "21160805", "Price": "€3.200", "Category": "Bike - Roller/Scooter", "Registration": "1 / 2012", "Mileage": "30,880 km", "Fuel type": "Gasoline", "Cubic capacity": "350 cc", "Power": "33 bhp", "Color": "Bordeaux", "Liters/100km": "42 (Εντός)", "Previous owners": "1", "Modified": "16 days", "Times clicked": "146", "Short link": "www.car.gr/21160805", "Telephone": "None"}, "ad_seller": {}, "metadata": {"type": "Bikes", "brand": "Piaggio", "model": "Beverly 350 SportTouring"}, "extras": [], "description": "Μόνο λάστιχα χρειάζεται. - Less - "}