{"query": {"url": "https://www.car.gr/20870566-yamaha-x-city-250", "type": "CAR_ADDE", "trial_count": 1, "last_processed": 1553102271}, "title": "Yamaha X-CITY 250  '08", "ad_id": "20870566", "ad_data": {"Make/Model": "Yamaha X-CITY 250 '08", "Classified number": "20870566", "Price": "€2.000", "Category": "Bike - Roller/Scooter", "Registration": "6 / 2008", "Mileage": "41,000 km", "Fuel type": "Gasoline", "Cubic capacity": "250 cc", "Power": "20 bhp", "Color": "Light Blue (Metallic)", "Modified": "29 days", "Times clicked": "18", "Short link": "www.car.gr/20870566", "Telephone": "None"}, "ad_seller": {}, "metadata": {"type": "Bikes", "brand": "Yamaha", "model": "X-CITY 250"}, "extras": [], "description": ""}