{"query": {"url": "https://www.car.gr/13243279-yamaha-t-max-500-blou-max", "type": "CAR_ADDE", "trial_count": 1, "last_processed": 1553093789}, "title": "Yamaha T-MAX 500 BLOU MAX '05", "ad_id": "13243279", "ad_data": {"Make/Model": "Yamaha T-MAX 500 BLOU MAX '05", "Classified number": "13243279", "Price": "€3.350", "Category": "Bike - Roller/Scooter", "Registration": "10 / 2005", "Mileage": "37,000 km", "Fuel type": "Gasoline", "Cubic capacity": "500 cc", "Power": "54 bhp", "Color": "Blue (Metallic)", "Kteo to": "10 / 2019", "Modified": "8 hours", "Times clicked": "5338", "Short link": "www.car.gr/13243279", "Telephone": "+30 2310557081"}, "ad_seller": {"Dealer": "!!!!!!!!!''*''*''AUTO GIANNITSON''*\"*\"!!!!!!!!!", "Address": "ΓΙΑΝΝΙΤΣΩΝ87", "City": "ΘΕΣΣΑΛΟΝΙΚΗ", "": "+30 2310557081", "Fax": "+30 2310557081", "Dealer page": "https//auto-giannitson.car.gr/", "Website": "http//''*''*''-AUTO GIANNITSON''*''*''"}, "metadata": {"type": "Bikes", "brand": "Yamaha", "model": "T-MAX 500"}, "extras": ["Automatic", "Car Exchange", "Centerstand", "Electric starter", "Exchange with Moto accepted", "Exhaust Special", "Four-stroke engine", "Gelatin", "Kick-Starter", "Sidestand"], "description": ""}