{"query": {"url": "https://www.car.gr/21115656-suzuki-fx-125", "type": "CAR_ADDE", "trial_count": 1, "last_processed": 1553100623}, "title": "Suzuki FX 125  '00", "ad_id": "21115656", "ad_data": {"Make/Model": "Suzuki FX 125 '00", "Classified number": "21115656", "Price": "€1.800", "Category": "Bike - Underbone", "Registration": "1 / 2000", "Mileage": "1,000 km", "Fuel type": "Gasoline", "Cubic capacity": "185 cc", "Power": "32 bhp", "Color": "Grey", "Modified": "19 days", "Times clicked": "702", "Short link": "www.car.gr/21115656", "Telephone": "None"}, "ad_seller": {}, "metadata": {"type": "Bikes", "brand": "Suzuki", "model": "FX 125"}, "extras": [], "description": "Πωλειται το παρον μηχανακι με πολυ προικα... - Περισσότερα σε τηλ - Less - "}