{"query": {"url": "https://www.car.gr/21480526-honda-cb-250-cb250", "type": "CAR_ADDE", "trial_count": 1, "last_processed": 1553094956}, "title": "Honda CB 250 CB250 '86", "ad_id": "21480526", "ad_data": {"Make/Model": "Honda CB 250 CB250 '86", "Classified number": "21480526", "Price": "€3.000", "Category": "Bike - Naked", "Registration": "9 / 1986", "Mileage": "36,000 km", "Fuel type": "Gasoline", "Cubic capacity": "248 cc", "Power": "26 bhp", "Color": "Black (Metallic)", "Liters/100km": "2 (Εντός)/3 (Μικτό)", "Modified": "2 days", "Times clicked": "33", "Short link": "www.car.gr/21480526", "Telephone": "None"}, "ad_seller": {}, "metadata": {"type": "Bikes", "brand": "Honda", "model": "CB 250"}, "extras": ["Antique-Classic", "Cargo Rack", "Centerstand", "Four-stroke engine", "Kick-Starter", "Sidestand", "Spoke wheels"], "description": "ΠΡΟΚΕΙΤΑΙ ΓΙΑ 2 ΜΗΧΑΝΕΣ, Η ΜΙΑ ΜΕ ΧΑΡΤΙΑ Η ΑΛΛΗ ΕΦΕΔΡΙΚΗ ΓΙΑ ΑΝΤΑΛΑΚΤΙΚΑ. - ΚΑΙ ΟΙ ΔΥΟ ΕΙΝΑΙ ΣΕ ΠΟΛΥ ΚΑΛΗ ΚΑΤΑΣΤΑΣΗ ΜΕ 29000 ΚΑΙ 36000 ΧΛΜ - ΠΩΛΟΥΝΤΑΙ ΜΟΝΟ ΜΑΖΙ ΣΥΝ ΑΡΚΕΤΑ ΟΛΟΚΑΙΝΟΥΡΓΙΑ ΑΝΤΑΛΑΚΤΙΚΑ ΚΑΙ ΑΠΟ ΜΙΑ ΒΑΛΙΤΣΑ. - Less - "}