{"query": {"url": "https://www.car.gr/21182891-honda-astrea-supra-100", "type": "CAR_ADDE", "trial_count": 1, "last_processed": 1553099713}, "title": "Honda Astrea Supra 100  '01", "ad_id": "21182891", "ad_data": {"Make/Model": "Honda Astrea Supra 100 '01", "Classified number": "21182891", "Price": "€700", "Category": "Bike - Underbone", "Registration": "10 / 2001", "Mileage": "90,000 km", "Fuel type": "Gasoline", "Cubic capacity": "100 cc", "Power": "13 bhp", "Color": "Blue (Metallic)", "Kteo to": "02 / 2019", "Liters/100km": "3 (Εντός)", "Modified": "14 days", "Times clicked": "879", "Short link": "www.car.gr/21182891", "Telephone": "None"}, "ad_seller": {}, "metadata": {"type": "Bikes", "brand": "Honda", "model": "Astrea Supra 100"}, "extras": ["Alarm", "Top Box-Μπαγκαζιέρα"], "description": "Άριστη κατάσταση μετά απο σέρβις. - Γνήσια χιλιόμετρα. - Όχι ντελιβεραδικο!!!! - Less - "}