{"query": {"url": "https://www.car.gr/20871502-bmw-r-1100-gs", "type": "CAR_ADDE", "trial_count": 1, "last_processed": 1553096403}, "title": "Bmw R 1100 GS  '98", "ad_id": "20871502", "ad_data": {"Make/Model": "Bmw R 1100 GS '98", "Classified number": "20871502", "Price": "€6.490", "Category": "Bike - Custom", "Registration": "1 / 1998", "Mileage": "3,300 km", "Fuel type": "Gasoline", "Cubic capacity": "1,100 cc", "Power": "90 bhp", "Color": "Grey (Metallic)", "Kteo to": "01 / 2020", "Liters/100km": "8 (Εντός)/8 (Εκτός)/8 (Μικτό)", "Modified": "5 days", "Times clicked": "629", "Short link": "www.car.gr/20871502", "Telephone": "None"}, "ad_seller": {}, "metadata": {"type": "Bikes", "brand": "Bmw", "model": "R 1100 GS"}, "extras": [], "description": "Κατασκευή scrambler από ιδιώτη με πολύ προσοχή και με γνήσια χλμ 70.000 .Το μηχανάκι είναι πλήρως λειτουργικό και χρησιμοποιείται καθημερινά όλα πάνω του είναι άκρως πρακτικά,φώτα,φλας φτερά εμπρός,πίσω κλπ. Λεπτομέρειες από το τηλέφωνο.. - Less - "}