{"query": {"url": "https://www.car.gr/13805476-kymco-downtown-300i", "type": "CAR_ADDE", "trial_count": 10, "last_processed": 1553092942}, "title": "Kymco Downtown 300i ## ΠΟΛΛΑ ΔΩΡΑ - ΑΡΙΣΤΟ ## '11", "ad_id": "13805476", "ad_data": {"Make/Model": "Kymco Downtown 300i ## ΠΟΛΛΑ ΔΩΡΑ - ΑΡΙΣΤΟ ## '11", "Classified number": "13805476", "Price": "€2.490", "Category": "Bike - Roller/Scooter", "Registration": "1 / 2011", "Mileage": "19,690 km", "Fuel type": "Gasoline", "Cubic capacity": "300 cc", "Power": "29 bhp", "Color": "Dark blue (Metallic)", "Modified": "2 hours", "Times clicked": "7053", "Short link": "www.car.gr/13805476", "Telephone": "+30 2351304835"}, "ad_seller": {"Dealer": "Auto Moto Group", "Address": "1ΧΛΜΚΑΤΕΡΙΝΗΣ-ΛΑΡΙΣΑΣ..(ΠΑΡΑΠΛΕΥΡΗΟΔΟΣ-ΠΑΡΑΔΡΟΜΟΣ)", "City": "ΚΑΤΕΡΙΝΗ", "": "+30 6938019020", "Dealer page": "https//auto-moto-group.car.gr/", "Website": "http//www.auto-moto-group.car.gr", "Open hours": "ΔΕΥΤΕΡΑ ΕΩΣ ΠΑΡΑΣΚΕΥΗ 0900-1700 ..\nΣΑΒΒΑΤΟ 1000-1500 ..\nΚΑΙ ΚΑΤΟΠΙΝ ΡΑΝΤΕΒΟΥ ΤΙΣ ΑΛΛΕΣ ΩΡΕΣ ΚΑΙ ΗΜΕΡΕΣ."}, "metadata": {"type": "Bikes", "brand": "Kymco", "model": "Downtown 300i"}, "extras": ["Automatic", "Car Exchange", "Cast wheels", "Centerstand", "Electric starter", "Exchange with Moto accepted", "Four-stroke engine", "Gelatin", "Kick-Starter", "Service Book", "Sidestand", "Spoke wheels", "Trip computer"], "description": "— ΔΩΡΕΑΝ ΑΠΟΣΤΟΛΗ ΓΙΑ ΑΘΗΝΑ ΠΑΡΑΛΑΒΗ ΑΠΟ ΑΣΠΡΟΠΥΡΓΟ Η ΕΛΕΥΣΙΝΑ - — ΔΩΡΟ Η ΜΕΤΑΒΙΒΑΣΗ - — ΔΩΡΟ ΤΕΛΗ 2019 - — ΣΕ ΠΑΡΑ ΠΟΛΥ ΚΑΛΗ ΚΑΤΑΣΤΑΣΗ - — ΚΑΙΝΟΥΡΓΙΟ ΕΛΑΣΤΙΚΟ ΕΜΠΡΟΣΘΙΟ - — ΚΑΙΝΟΥΡΓΙΑ ΜΠΑΤΑΡΙΑ - — AΠΟ SERVICE ΣΕ ΑΝΤΙΠΡΟΣΩΠΕΙΑ ΚYMCO - — ΔΩΡΟ ΚΤΕΟ ΓΙΑ 2 ΧΡΟΝΙΑ - — ΔΕΚΤΟΣ ΚΑΘΕ ΕΛΕΓΧΟΣ - Less - "}