{"query": {"url": "https://www.car.gr/20325394-yamaha-tdm-900-a-touring-packet", "type": "CAR_ADDE", "trial_count": 1, "last_processed": 1553099991}, "title": "Yamaha TDM 900 A Touring Packet '06", "ad_id": "20325394", "ad_data": {"Make/Model": "Yamaha TDM 900 A Touring Packet '06", "Classified number": "20325394", "Price": "€4.000", "Category": "Bike - On/Off", "Registration": "3 / 2006", "Mileage": "42,000 km", "Fuel type": "Gasoline", "Cubic capacity": "900 cc", "Power": "86 bhp", "Color": "Dark blue (Metallic)", "Kteo to": "01 / 2020", "Liters/100km": "5 (Μικτό)", "Modified": "16 days", "Times clicked": "309", "Short link": "www.car.gr/20325394", "Telephone": "None"}, "ad_seller": {}, "metadata": {"type": "Bikes", "brand": "Yamaha", "model": "TDM 900 A"}, "extras": ["ABS", "Alarm", "Electric starter", "Engine Guards", "Gelatin", "Heated Handguards", "Kick-Starter", "Lights Xenon"], "description": "*Σε πολύ καλή κατάσταση! Δίνεται λόγω έλλειψης χρόνου. - *ΑΤΡΑΚΑΡΙΣΤΟ - *ΠΡΑΓΜΑΤΙΚΑ ΧΙΛΙΟΜΕΤΡΑ ( Όπως βλέπεται η συγκεκριμένη μηχανή έχει χαρακτήρα Touring. - Σχεδόν όλα τα χιλιόμετρα έχουν γίνει σε ταξίδια.) - *Συντήρηση πάντα στην ώρα του! - *Καινούρια ελαστικά. (Τα λάστιχα δεν έχουν κάνει ούτε 1000 χλμ.) - *ΠΟΛΛΑ ΕΞΤΡΑ: -Συναγερμός beta -ΚΑΓΚΕΛΑ ΚΑΙ ΒΑΛΙΤΣΕΣ GIVI -Θερμαινόμενα grip -Χούφτες -3 κλειδιά -προστατευτικά κάγκελα -Bagster Tdm - Σέλα ανατομική - 3 ανεμοθραύστες - 52 Lt μπαγκαζιέρα -ανάρτηση auler -αλυσίδα χρυσή DID -xenon φώτα - Less - "}