{"query": {"url": "https://www.car.gr/20222168-suzuki-v-strom-650", "type": "CAR_ADDE", "trial_count": 1, "last_processed": 1553095736}, "title": "Suzuki V-Strom 650  '11", "ad_id": "20222168", "ad_data": {"Make/Model": "Suzuki V-Strom 650 '11", "Classified number": "20222168", "Price": "€5.500", "Category": "Bike - On/Off", "Registration": "1 / 2011", "Mileage": "46,700 km", "Fuel type": "Gasoline", "Cubic capacity": "650 cc", "Power": "70 bhp", "Color": "White (Metallic)", "Modified": "3 days", "Times clicked": "48", "Short link": "www.car.gr/20222168", "Telephone": "None"}, "ad_seller": {}, "metadata": {"type": "Bikes", "brand": "Suzuki", "model": "V-Strom 650"}, "extras": ["ABS", "Alarm", "Centerstand", "Electric starter", "Engine Guards", "Exchange with Moto accepted", "Gelatin", "Injection", "Kick-Starter", "Led lights", "Service Book", "Sidestand", "Top Box-Μπαγκαζιέρα"], "description": "Η μηχανή είναι σε άριστη κατάσταση προσεγμένη full extra, χούφτες,φτερό πίσω ζάντας πιό μεγάλο .ζελατίνα φιμέ με προέκταση, συναγερμός φώτα LED καινούργια με διακόπτη on/off, καρίνα, αναπτήρας κάτω απο τη σέλα για φόρτιση κινητού, κεντρικό διπλό στάντ ,μπαγκαζιέρα προστατευτικό κάλυμμα εξάτμισης, κάγκελα προστασίας ,tanklock βαλιτσάκι ντεπόζιτου 20lt -2 πλαινές βαλίτσες kappa σχεδόν αχρησιμοποίητες όπως και βαλιτσάκια για τα μπροστινά κάγκελα γνήσια suzuki ,Καινούργια τακάκια-καινούργια μπρος πίσω καινουργια αλυσιδοργάναζα did καινουργια σελα Παρακαλώ μόνο σοβαρές προτάσεις. - Less - "}