{"query": {"url": "https://www.car.gr/20321753-honda-cbr-125r", "type": "CAR_ADDE", "trial_count": 1, "last_processed": 1553103933}, "title": "Honda CBR 125R  '08", "ad_id": "20321753", "ad_data": {"Make/Model": "Honda CBR 125R '08", "Classified number": "20321753", "Price": "€1.400", "Category": "Bike - On/Off", "Registration": "1 / 2008", "Mileage": "9,608 km", "Fuel type": "Gasoline", "Cubic capacity": "125 cc", "Power": "21 bhp", "Color": "Red (Metallic)", "Modified": "44 days", "Times clicked": "347", "Short link": "www.car.gr/20321753", "Telephone": "None"}, "ad_seller": {}, "metadata": {"type": "Bikes", "brand": "Honda", "model": "CBR 125R"}, "extras": [], "description": "Σαν καινούριο δεν χρειάζεται ούτε ευρώ.πραγματικα χιλιόμετρα.η τιμή είναι λίγο συζητήσιμη.πραγματικη ευκαιρία!!!!!!!!!!ανταλαγη με αυτοματο - Less - "}