{"query": {"url": "https://www.car.gr/12057789-yamaha-yzf-r1", "type": "CAR_ADDE", "trial_count": 1, "last_processed": 1553094435}, "title": "Yamaha YZF-R1  '09", "ad_id": "12057789", "ad_data": {"Make/Model": "Yamaha YZF-R1 '09", "Classified number": "12057789", "Price": "€8.995", "Category": "Bike - Super Sport", "Registration": "6 / 2009", "Mileage": "23,000 km", "Fuel type": "Gasoline", "Cubic capacity": "1,000 cc", "Power": "190 bhp", "Color": "Black", "Modified": "22 hours", "Times clicked": "14775", "Short link": "www.car.gr/12057789", "Telephone": "+30 2107480575"}, "ad_seller": {"Dealer": "FACTORY MOTO", "Address": "MIXAΛΑΚΟΠΟΥΛΟΥ173", "City": "ΑΘΗΝΑ", "": "+30 6994796560", "Fax": "+30 2107480572", "Dealer page": "https//factorymoto.car.gr/", "Website": "http//www.factorymoto.gr"}, "metadata": {"type": "Bikes", "brand": "Yamaha", "model": "YZF-R1"}, "extras": ["Exchange with Moto accepted", "Exhaust Special", "Gelatin", "Service Book", "Sidestand"], "description": "-ΔΕΚΤΟΣ ΚΑΘΕ ΤΕΧΝΙΚΟΣ ΕΛΕΓΧΟΣ -ΚΑΙ ΜΕ ΔΟΣΕΙΣ ΑΠΟ 0% ΠΡΟΚΑΤΑΒΟΛΗ ΚΑΙ ΕΞΟΦΛΗΣΗ ΕΩΣ 72 ΜΗΝΕΣ -ΚΑΙ ΜΕ ΤΗΝ ΠΙΣΤΩΤΙΚΗ ΣΑΣ ΚΑΡΤΑ -ΔΕΚΤΗ ΚΑΙ Η ΜΟΤΟΣΥΚΛΕΤΑ ΣΑΣ ΓΙΑ ΑΝΤΑΛΛΑΓΗ -ΔΥΝΑΤΟΤΗΤΑ ΑΠΟΣΤΟΛΗΣ ΣΕ ΟΛΗ ΤΗΝ ΕΛΛΑΔΑ - ΤΟ ΜΗΧΑΝΑΚΙ ΔΙΑΘΕΤΕΙ ΕΞΑΤΜΙΣΕΙΣ TERMIGNONI, ΖΕΛΑΤΙΝΑ AIRMAX, ΜΑΝΙΤΑΡΙΑ BARRACUNA, ΧΕΙΡΟΛΑΒΕΣ GRIP - ΔΩΡΟ ΤΟ ΣΗΜΑ 2018 - ΤΗΛΕΦΩΝΗΣΤΕ ΓΙΑ ΔΙΑΘΕΣΙΜΟΤΗΤΑ - Less - "}