{"query": {"url": "https://www.car.gr/14828461-honda-c50-12v", "type": "CAR_ADDE", "trial_count": 1, "last_processed": 1553101615}, "title": "Honda  C50 12V '70", "ad_id": "14828461", "ad_data": {"Make/Model": "Honda C50 12V '70", "Classified number": "14828461", "Price": "€2.300", "Category": "Bike - Underbone", "Registration": "7 / 1970", "Fuel type": "Gasoline", "Cubic capacity": "50 cc", "Power": "6 bhp", "Color": "Dark Red", "Liters/100km": "2.2 (Εντός)", "Previous owners": "1", "Modified": "24 days", "Times clicked": "220", "Short link": "www.car.gr/14828461", "Telephone": "None"}, "ad_seller": {"Name": "MARIA", "Address": "ΜΥΤΙΛΗΝΗP.ΛΕΣΒΟΥ"}, "metadata": {"type": "Bikes", "brand": "Honda", "model": "Honda  C50 12V '70 - € 2.300 EUR (Negotiable)"}, "extras": ["Antique-Classic", "Car Exchange", "Centerstand", "Exchange with Boat", "Exchange with Moto accepted", "Exhibition", "Four-stroke engine", "Sidestand", "Spoke wheels"], "description": "Το παπί είναι ανακατασκευή όλα από την αρχή. - Less - "}