{"query": {"url": "https://www.car.gr/12175839-honda-cbr-1000rr", "type": "CAR_ADDE", "trial_count": 1, "last_processed": 1553094471}, "title": "Honda CBR 1000RR  '05", "ad_id": "12175839", "ad_data": {"Make/Model": "Honda CBR 1000RR '05", "Classified number": "12175839", "Price": "€3.800", "Category": "Bike - Super Sport", "Registration": "11 / 2005", "Mileage": "47,500 km", "Fuel type": "Gasoline", "Cubic capacity": "1,000 cc", "Power": "180 bhp", "Color": "Red", "Kteo to": "05 / 2020", "Liters/100km": "5 (Εντός)/5 (Εκτός)/5 (Μικτό)", "Modified": "24 hours", "Times clicked": "952", "Short link": "www.car.gr/12175839", "Telephone": "None"}, "ad_seller": {"Name": "Γιώργος", "Address": "ΡΕΘΥΜΝΟP.ΡΕΘΥΜΝΗΣ"}, "metadata": {"type": "Bikes", "brand": "Honda", "model": "CBR 1000RR"}, "extras": ["Car Exchange", "Electric starter", "Exchange with Moto accepted", "Exhaust Special", "Four-stroke engine", "Injection"], "description": "Άψογη κατάσταση, δεκτος έλεγχος όπου θέλετε. - Απο extra εχει - *Ολόσωμη τιτανίου ARATA - *Φίλτρο ελευθέρας ΚΝ - *Μανέτες SP - *Carbon γνήσιο φτερό - *Gear indicator - *Μανιτάρια - *Λάστιχα pirelli diablo roso μπήκαν τον Μάιο - *Αλυσιδογραναζα AFAM 530 XS-RING μπήκα και αυτά Μάιο - Σερβις στις μπουκάλες αλλαγμένες ξύστρες και τσιμούχες - *Μονόσελο - *Led πίσω φανάρι με ενσωματομένο φλας - Τα έξτρα περνάνε τα 3.000€ - Μαζί δίνονται όλα τα εργοστάσια πράγματα(λασπωτηρες, φλας, καθρέφτες, εξάτμιση). - Η τιμή χωρίς εξάτμιση θα κατευει στα 3500. - Less - "}