{"query": {"url": "https://www.car.gr/18436222-bmw-k-1300gt-anniversary", "type": "CAR_ADDE", "trial_count": 1, "last_processed": 1553095290}, "title": "Bmw K 1300GT anniversary '11", "ad_id": "18436222", "ad_data": {"Make/Model": "Bmw K 1300GT anniversary '11", "Classified number": "18436222", "Price": "€10.800", "Category": "Bike - Sport Touring", "Registration": "2 / 2011", "Mileage": "61,000 km", "Fuel type": "Gasoline", "Cubic capacity": "1,300 cc", "Power": "160 bhp", "Color": "Light Blue (Metallic)", "Kteo to": "01 / 2020", "Previous owners": "1", "Modified": "2 days", "Times clicked": "966", "Short link": "www.car.gr/18436222", "Telephone": "None"}, "ad_seller": {}, "metadata": {"type": "Bikes", "brand": "Bmw", "model": "K 1300GT"}, "extras": ["ABS", "Alarm", "Cast wheels", "Centerstand", "Four-stroke engine", "Gelatin", "Heated Handguards", "Injection", "Led lights", "Sidestand", "TCS-TractionControl", "Top Box-Μπαγκαζιέρα", "Trip computer"], "description": "Η ΜΗΧΑΝΗ ΕΊΝΑΙ ΣΕ ΆΡΙΣΤΗ ΚΑΤΆΣΤΑΣΗ ΌΛΑ ΤΑ ΧΙΛΙΌΜΕΤΡΑ ΕΙΝΑΙ ΜΌΝΟ ΣΕ ΤΑΞΊΔΙΑ ΚΑΙ ΠΟΤΈ ΧΩΜΑ - ΟΛΑ ΤΑ SERVICE ΣΤΗΝ ΕΠΊΣΗΜΗ ΑΝΤΙΠΡΟΣΩΠΕΊΑ - Less - "}