{"query": {"url": "https://www.car.gr/11712103-piaggio-mp3-400-lt", "type": "CAR_ADDE", "trial_count": 1, "last_processed": 1553104942}, "title": "Piaggio  MP3 400 LT '15", "ad_id": "11712103", "ad_data": {"Make/Model": "Piaggio MP3 400 LT '15", "Classified number": "11712103", "Price": "Askforprice", "Category": "Bike - Roller/Scooter", "Registration": "1 / 2015", "Fuel type": "Gasoline", "Cubic capacity": "300 cc", "Power": "22 bhp", "Color": "Blue", "Modified": "11 hours", "Times clicked": "1864", "Short link": "www.car.gr/11712103", "Telephone": "+30 2105561511"}, "ad_seller": {"Dealer": "MOTODROULIAS", "Address": "ΣΟΥΛΙΟΥ73", "City": "ΕΛΕΥΣΙΝΑ", "": "+30 2296089266", "Dealer page": "https//motodroulias.car.gr/"}, "metadata": {"type": "Bikes", "brand": "Piaggio", "model": "Piaggio  MP3 400 LT '15 - Ask for price"}, "extras": [], "description": "ANTAΛΛΑΚΤΙΚΑ ΜΕΤΑΧΕΙΡΙΣΜΕΝΑ ΜP3 LT - Less - "}