{"query": {"url": "https://www.car.gr/3883873-tcb-spark-125-50-125", "type": "CAR_ADDE", "trial_count": 1, "last_processed": 1553099727}, "title": "TCB Spark 125 50-125 '13", "ad_id": "3883873", "ad_data": {"Make/Model": "TCB Spark 125 50-125 '13", "Classified number": "3883873", "Price": "€1.150", "Category": "Bike - Roller/Scooter", "Registration": "1 / 2013", "Fuel type": "Gasoline", "Cubic capacity": "50 cc", "Power": "5 bhp", "Color": "Black", "Modified": "15 days", "Times clicked": "3207", "Short link": "www.car.gr/3883873", "Telephone": "+30 2109712304"}, "ad_seller": {"Dealer": "Συνεργείο μοτο, ηλεκτρικά, ανταλακτικά-αξεσουάρ-πωλήσεις ΜΟΤΟ καινούριων και μεταχειρισμένων-ΣΤΕΛΙΟΣ", "Address": "ΛΕΩΦ.ΔΗΜΟΚΡΑΤΙΑΣ43ΗΛΙΟΥΠΟΛΗ", "City": "ΗΛΙΟΥΠΟΛΗ", "": "+30 2109712304", "Fax": "+30 2109712304", "Dealer page": "https//stelioss.car.gr/"}, "metadata": {"type": "Bikes", "brand": "TCB", "model": "Spark 125"}, "extras": [], "description": " Άδεια 50 κυβικά. - Με εργοστασιακά βελτιωμένο κινητήρα, με αυξημένη ιπποδύναμη (με περισσότερα κυβικά). - Διατίθεται και σε 125 κυβικά, στην ίδια τιμή. - Less - "}