{"query": {"url": "https://www.car.gr/16556407-lifan-city-125", "type": "CAR_ADDE", "trial_count": 1, "last_processed": 1553102796}, "title": "Lifan CITY 125  '06", "ad_id": "16556407", "ad_data": {"Make/Model": "Lifan CITY 125 '06", "Classified number": "16556407", "Price": "€300", "Category": "Bike - Roller/Scooter", "Registration": "9 / 2006", "Mileage": "45,000 km", "Fuel type": "Gasoline", "Cubic capacity": "125 cc", "Power": "12 bhp", "Color": "Silver", "Previous owners": "1", "Modified": "34 days", "Times clicked": "407", "Short link": "www.car.gr/16556407", "Telephone": "None"}, "ad_seller": {}, "metadata": {"type": "Bikes", "brand": "Lifan", "model": "CITY 125"}, "extras": [], "description": "Για ανταλλακτικά,δουλεύει κανονικά. Έχουν παραδοθεί πινακίδες. - Less - "}