{"query": {"url": "https://www.car.gr/18270338-yamaha-tw-125-125", "type": "CAR_ADDE", "trial_count": 10, "last_processed": 1553092954}, "title": "Yamaha TW 125 125 '07", "ad_id": "18270338", "ad_data": {"Make/Model": "Yamaha TW 125 125 '07", "Classified number": "18270338", "Price": "€1.200", "Category": "Bike - On/Off", "Registration": "1 / 2007", "Mileage": "18,357 km", "Fuel type": "Gasoline", "Cubic capacity": "125 cc", "Power": "15 bhp", "Color": "Dark blue (Metallic)", "Kteo to": "11 / 2020", "Previous owners": "1", "Modified": "3 hours", "Times clicked": "1140", "Short link": "www.car.gr/18270338", "Telephone": "+30 2251048500"}, "ad_seller": {"Dealer": "AUTOLESVOS.GR AUTOLESVOS.GR", "Address": "8ΧΙΛΚΑΛΛΟΝΗΣΜΥΤIΛΗΝΗΣ", "City": "ΚΑΛΛΟΝΗ", "": "+30 2251048500", "Fax": "+30 2253032200", "Dealer page": "https//autolesvosgr.car.gr/", "Website": "http//autolesvos.gr"}, "metadata": {"type": "Bikes", "brand": "Yamaha", "model": "TW 125"}, "extras": ["Car Exchange", "Electric starter", "Exchange with Boat", "Exchange with Moto accepted", "Four-stroke engine", "Service Book", "Sidestand"], "description": "ΑΠΟΣΤΟΛΗ ΣΕ ΟΛΗ ΤΗΝ ΕΛΛΑΔΑ. - Less - "}