{"query": {"url": "https://www.car.gr/20907434-yamaha-fz6-fazer-fz6n", "type": "CAR_ADDE", "trial_count": 1, "last_processed": 1553094875}, "title": "Yamaha FZ6 Fazer FZ6N '06", "ad_id": "20907434", "ad_data": {"Make/Model": "Yamaha FZ6 Fazer FZ6N '06", "Classified number": "20907434", "Price": "€2.600", "Category": "Bike - Naked", "Registration": "6 / 2006", "Mileage": "72,000 km", "Fuel type": "Gasoline", "Cubic capacity": "600 cc", "Power": "98 bhp", "Color": "Black (Metallic)", "Kteo to": "10 / 2020", "Modified": "2 days", "Times clicked": "543", "Short link": "www.car.gr/20907434", "Telephone": "None"}, "ad_seller": {"Name": "KonstantinosC.", "Address": "ΚΑΛΛΙΘΕΑP.ΑΤΤΙΚΗΣ"}, "metadata": {"type": "Bikes", "brand": "Yamaha", "model": "FZ6 Fazer"}, "extras": ["Alarm", "Four-stroke engine", "Injection", "Sidestand", "Spoke wheels", "Trip computer"], "description": "FZ6 FAZER NAKED 06' - ΜΑΎΡΟ ΣΑΣΊ-ΜΑΥΡΟΣ ΚΙΝΗΤΉΡΑΣ - BAGSTER - ΜΑΝΙΤΆΡΙΑ - ΣΥΝΑΓΕΡΜΟΣ SPYBALL - ΑΠΌ ΣΕΡΒΙΣ - ΚΑΙΝΟΥΡΙΑ ΜΠΑΤΑΡΊΑ - ΛΆΣΤΙΧΑ MICHELEN PILOT ROAD 4 - ΑΝΤΙΟΛΙΣΘΗΤΙΚΗ ΣΕΛΑ - ΠΛΗΡΩΜΈΝΑ ΤΈΛΗ 2019 - ΚΤΕΟ ΕΩΣ 2020 - ΔΕΚΤΟΣ ΈΛΕΓΧΟΣ - ΤΟ ΜΗΧΑΝΆΚΙ ΕΊΝΑΙ ΣΕ ΑΡΙΣΤΗ ΚΑΤΑΣΤΑΣΗ ΔΕΝ ΧΡΕΙΆΖΕΤΑΙ ΤΠΤ. - ΤΟ ΧΕΙΜΏΝΑ ΕΊΝΑΙ ΚΛΕΙΣΤΌ ΜΕ ΚΟΥΚΟΎΛΑ ΚΑΙ ΒΓΑΛΜΈΝΗ ΜΠΑΤΑΡΊΑ. - ΟΛΑ ΠΆΝΩ ΤΟΥ ΕΊΝΑΙ YAMAHA ΔΕΝ ΈΧΩ ΠΕΙΡΆΞΕΙ ΤΠΤ. - ΔΊΝΟΝΤΑΙ ΜΑΖΊ Η ΕΡΓΟΣΤΑΣΙΑΚΉ ΒΆΣΗ ΠΙΝΑΚΙΔΑΣ, ΚΛΕΙΔΑΡΙΆ ΔΙΣΚΌΦΡΕΝΟΥ, ΚΟΥΚΟΎΛΑ ΜΗΧΑΝΉΣ. - Less - "}