{"query": {"url": "https://www.car.gr/13506155-honda-pcx-150-start-stop", "type": "CAR_ADDE", "trial_count": 1, "last_processed": 1553105334}, "title": "Honda PCX 150 START STOP-ΤΕΤΡΑΧΡΟΝΟ-ΑΡΙΣΤΟ '14", "ad_id": "13506155", "ad_data": {"Make/Model": "Honda PCX 150 START STOP-ΤΕΤΡΑΧΡΟΝΟ-ΑΡΙΣΤΟ '14", "Classified number": "13506155", "Price": "Askforprice", "Category": "Bike - Roller/Scooter", "Registration": "1 / 2014", "Mileage": "14,900 km", "Fuel type": "Gasoline", "Cubic capacity": "150 cc", "Power": "15 bhp", "Color": "White (Metallic)", "Previous owners": "1", "Modified": "20 days", "Times clicked": "3985", "Short link": "www.car.gr/13506155", "Telephone": "+30 2321038630"}, "ad_seller": {"Dealer": "ΑΥΤΟΚΙΝΗΤΑ ΠΑΝΤΑΖΗΣ", "Address": "1ΧλμΣερρώνΝιγρίτας", "City": "ΣΕΡΡΕΣ", "": "+30 2321036890", "Fax": "+30 2321037509", "Dealer page": "https//auto-pantazis.car.gr/"}, "metadata": {"type": "Bikes", "brand": "Honda", "model": "PCX 150"}, "extras": ["Automatic", "Cast wheels", "Centerstand", "Electric starter", "Four-stroke engine", "Gelatin", "Kick-Starter", "Top Box-Μπαγκαζιέρα"], "description": "START STOP-ΤΕΤΡΑΧΡΟΝΟ-ΑΡΙΣΤΟ!! - Less - "}