{"query": {"url": "https://www.car.gr/21007189-kawasaki-kle-500-kle-500", "type": "CAR_ADDE", "trial_count": 8, "last_processed": 1553093014}, "title": "Kawasaki KLE 500 KLE 500       '98", "ad_id": "21007189", "ad_data": {"Make/Model": "Kawasaki KLE 500 KLE 500       '98", "Classified number": "21007189", "Price": "€1.000", "Category": "Bike - On/Off", "Registration": "8 / 1998", "Mileage": "95,000 km", "Fuel type": "Gasoline", "Cubic capacity": "500 cc", "Power": "50 bhp", "Color": "Gold (Metallic)", "Kteo to": "01 / 2019", "Previous owners": "1", "Modified": "4 hours", "Times clicked": "848", "Short link": "www.car.gr/21007189", "Telephone": "None"}, "ad_seller": {"Name": "costas", "Address": "Σ.Σ.ΒΑΡΔΑΣP.ΑΧΑΪΑΣ"}, "metadata": {"type": "Bikes", "brand": "Kawasaki", "model": "KLE 500"}, "extras": ["Bars", "Electric starter", "Engine Guards", "Four-stroke engine", "Gelatin", "Sidestand", "Skid Plate", "Spoke wheels", "Top Box-Μπαγκαζιέρα"], "description": "aristi katastasi.poli prosegmeni.ola ta servise stinora tous - Less - "}