{"query": {"url": "https://www.car.gr/6284751-honda-xx-1100", "type": "CAR_ADDE", "trial_count": 1, "last_processed": 1553095347}, "title": "Honda  XX 1100 '00", "ad_id": "6284751", "ad_data": {"Make/Model": "Honda XX 1100 '00", "Classified number": "6284751", "Price": "€4.000", "Category": "Bike - Super Sport", "Registration": "1 / 2000", "Mileage": "20,000 km", "Fuel type": "Gasoline", "Cubic capacity": "1,100 cc", "Power": "3 bhp", "Color": "Blue", "Modified": "7 minutes", "Times clicked": "5078", "Short link": "www.car.gr/6284751", "Telephone": "+30 2109594592"}, "ad_seller": {"Dealer": "HONDA MOTO", "Address": "ΑΡΓΥΡΟΥΠΟΛΕΩΣ5", "City": "ΚΑΛΛΙΘΕΑ", "": "+30 2109594592", "Fax": "+30 2109594592", "Dealer page": "https//mitilineos-honda.car.gr/"}, "metadata": {"type": "Bikes", "brand": "Honda", "model": "Honda  XX 1100 '00 - € 4.000 EUR"}, "extras": [], "description": "XX 1100 - του 2000 - 4.000E - Less - "}