{"query": {"url": "https://www.car.gr/20957227-honda-cub-c90", "type": "CAR_ADDE", "trial_count": 1, "last_processed": 1553102030}, "title": "Honda  CUB C90 '91", "ad_id": "20957227", "ad_data": {"Make/Model": "Honda CUB C90 '91", "Classified number": "20957227", "Price": "€1.100", "Category": "Bike - Underbone", "Registration": "12 / 1991", "Mileage": "46,000 km", "Fuel type": "Gasoline", "Cubic capacity": "90 cc", "Power": "10 bhp", "Color": "Dark Red", "Kteo to": "01 / 2020", "Modified": "27 days", "Times clicked": "108", "Short link": "www.car.gr/20957227", "Telephone": "None"}, "ad_seller": {}, "metadata": {"type": "Bikes", "brand": "Honda", "model": "Honda  CUB C90 '91 - € 1.100 EUR"}, "extras": ["Centerstand", "Electric starter", "Greek Dealership", "Semiautomatic", "Service Book", "Sidestand", "Spoke wheels", "Top Box-Μπαγκαζιέρα", "Καρμπυρατέρ"], "description": "πρωτο χερι δεν εχει ανοιχτει ποτε το μοτερ γενικα αψογο πωλειται λογω ηλικιας μου - Less - "}