{"query": {"url": "https://www.car.gr/20239254-piaggio-skipper", "type": "CAR_ADDE", "trial_count": 1, "last_processed": 1553096841}, "title": "Piaggio Skipper  '04", "ad_id": "20239254", "ad_data": {"Make/Model": "Piaggio Skipper '04", "Classified number": "20239254", "Price": "€650", "Category": "Bike - Roller/Scooter", "Registration": "6 / 2004", "Mileage": "49,000 km", "Fuel type": "Gasoline", "Cubic capacity": "125 cc", "Power": "12 bhp", "Color": "Blue", "Kteo to": "12 / 2019", "Liters/100km": "3.5 (Εντός)/3.7 (Εκτός)/3.6 (Μικτό)", "Previous owners": "1", "Modified": "7 days", "Times clicked": "49", "Short link": "www.car.gr/20239254", "Telephone": "None"}, "ad_seller": {}, "metadata": {"type": "Bikes", "brand": "Piaggio", "model": "Skipper"}, "extras": ["Exchange with Moto accepted"], "description": "ΠΩΛΕΙΤΑΙ ΣΕ ΑΡΙΣΤΗ ΚΑΤΑΣΤΑΣΗ. - ΑΛΗΘΙΝΑ ΧΙΛΙΟΜΕΤΡΑ. - ΣΩΣΤΑ ΣΥΝΤΗΡΗΜΕΝΟ. - ΠΕΡΑΣΜΕΝΟ ΚΤΕΟ,ΚΑΘΑΡΟ ΜΕ ΟΛΑ ΤΟΥ ΤΑ ΧΑΡΤΙΑ. - ΑΠΡΟΒΛΗΜΑΤΙΣΤΟ ΚΑΙ ΑΝΤΟΧΗΣ ΜΗΧΑΝΑΚΙ. - ΜΕ ΜΠΑΓΚΑΖΙΕΡΑ ΜΑΝΙΣΙΑ,ΧΟΥΦΤΕΣ,ΜΙΚΡΟ ΑΝΕΜΟΘΩΡΑΚΑ ΚΑΙ ΠΟΛΛΟΥΣ ΧΩΡΟΥΣ. - ΚΕΝΤΡΙΚΟ ΚΑΙ ΠΛΑΓΙΟ ΣΤΑΝΤ. - ΔΕΚΤΟΣ ΚΑΘΕ ΕΛΕΓΧΟΣ. - ΤΕΛΙΚΗ ΤΙΜΗ. - Πληροφοριες: - Less - "}