{"query": {"url": "https://www.car.gr/14775724-yamaha-majesty-150", "type": "CAR_ADDE", "trial_count": 1, "last_processed": 1553104757}, "title": "Yamaha Majesty 150  '17", "ad_id": "14775724", "ad_data": {"Make/Model": "Yamaha Majesty 150 '17", "Classified number": "14775724", "Price": "€2.400", "Category": "Bike - Roller/Scooter", "Registration": "1 / 2017", "Mileage": "6,500 km", "Fuel type": "Gasoline", "Cubic capacity": "155 cc", "Power": "12 bhp", "Color": "Grey", "Modified": "over 2 months", "Times clicked": "639", "Short link": "www.car.gr/14775724", "Telephone": "+30 2310502080"}, "ad_seller": {"Dealer": "ΜΟΤΟ ΚΑΠΟΥΣΗΣ", "Address": "ΛΑΓΚΑΔΑ134", "City": "ΝΕΑΠΟΛΗ", "": "+30 2310502080", "Dealer page": "https//motokapousis.car.gr/", "Open hours": "Δευτέρα εως Παρασκεύη\n 09.00-19.00 και \nΣάββατο απο 09.00 εως 14.00"}, "metadata": {"type": "Bikes", "brand": "Yamaha", "model": "Majesty 150"}, "extras": [], "description": ""}