{"query": {"url": "https://www.car.gr/17130080-yamaha-fz6-fazer", "type": "CAR_ADDE", "trial_count": 1, "last_processed": 1553094745}, "title": "Yamaha FZ6 Fazer  '08", "ad_id": "17130080", "ad_data": {"Make/Model": "Yamaha FZ6 Fazer '08", "Classified number": "17130080", "Price": "€2.650", "Category": "Bike - Sport Touring", "Registration": "3 / 2008", "Mileage": "46,098 km", "Fuel type": "Gasoline", "Cubic capacity": "600 cc", "Power": "100 bhp", "Color": "Black (Metallic)", "Kteo to": "05 / 2019", "Previous owners": "2", "Modified": "1 day", "Times clicked": "7007", "Short link": "www.car.gr/17130080", "Telephone": "None"}, "ad_seller": {}, "metadata": {"type": "Bikes", "brand": "Yamaha", "model": "FZ6 Fazer"}, "extras": ["Car Exchange", "Centerstand", "Electric starter", "Exchange with Moto accepted", "Exhibition", "Four-stroke engine", "Gelatin", "Injection", "Led lights", "Lights Xenon", "Sidestand"], "description": "ΑΛΛΑΓΗ ΛΑΔΙΩΝ ,ΦΙΛΤΡΟΥ ΚΑΙ ΠΑΡΑΦΛΟΥ ΛΙΑΝ ΠΡΟΣΦΑΤΩΣ ,ΚΑΙΝΟΥΡΓΙΑ ΤΑΚΑΚΙΑ YAMAHA ΤΙΜΟΝΙ FLAT BAR ΑΠΟ FZ1000, ΖΕΛΑΤΙΝΑ ΧΕΙΡΟΠΟΙΗΤΗ DOUBLE BUBLE ΑΓΩΝΙΣΤΙΚΟΥ ΤΥΠΟΥ,ΦΙΛΤΡΟ ΚΝ ,ΛΑΜΠΕΣ LED ΜΙΚΡΗ ΣΚΑΛΑ,ΜΕΓΑΛΗ ΚΑΙ ΤΑ ΣΠΟΤΑΚΙΑ, ΜΑΖΙ ΔΥΝΟΝΤΑΙ ΒΑΣΗ ΠΙΝΑΚΙΔΑΣ ΤΟ ΜΑΜΑ ΤΙΜΟΝΙ ΚΑΙ Η ΜΑΜΑ ΖΕΛΑΤΙΝΑ!!!ΟΧΙ ΑΠΟΚΡΥΨΕΙΣ!!!ΕΠΙΚΟΙΝΩΝΗΣΤΕ ΜΑΖΙ ΜΟΥ ΣΕ ΛΟΓΙΚΕΣ ΩΡΕΣ!!!ΟΧΙ ΠΑΖΑΡΙΑ!!!ΤΕΛΙΚΗ ΤΙΜΗ !!!!!!!!ΠΛΗΡΩΜΕΝΟ ΣΗΜΑ 2019!!! ΛΟΓΟ ΑΝΑΓΚΗΣ ΟΙΚΟΝΟΜΙΚΗΣ !!! - Less - "}