{"query": {"url": "https://www.car.gr/13581374-kawasaki-z-750-750", "type": "CAR_ADDE", "trial_count": 1, "last_processed": 1553101687}, "title": "Kawasaki Z 750 Ζ 750 '04", "ad_id": "13581374", "ad_data": {"Make/Model": "Kawasaki Z 750 Ζ 750 '04", "Classified number": "13581374", "Price": "€2.300", "Category": "Bike - Naked", "Registration": "6 / 2004", "Mileage": "34,000 km", "Fuel type": "Gasoline", "Cubic capacity": "750 cc", "Power": "115 bhp", "Color": "Black (Metallic)", "Kteo to": "05 / 2019", "Modified": "24 days", "Times clicked": "927", "Short link": "www.car.gr/13581374", "Telephone": "None"}, "ad_seller": {"Name": "ΒΑΣΙΛΗΣ", "Address": "ΛΟΥΤΡΑΚΙP.ΚΟΡΙΝΘΙΑΣ"}, "metadata": {"type": "Bikes", "brand": "Kawasaki", "model": "Z 750"}, "extras": [], "description": "το μηχανακι ειναι προσεγμένο με τα service του.δεν εχει μπει πιστα. - Less - "}