{"query": {"url": "https://www.car.gr/16560327-honda-cbf-600s-cbf600s", "type": "CAR_ADDE", "trial_count": 1, "last_processed": 1553094630}, "title": "Honda CBF 600S CBF600S '07", "ad_id": "16560327", "ad_data": {"Make/Model": "Honda CBF 600S CBF600S '07", "Classified number": "16560327", "Price": "€3.100", "Category": "Bike - Sport Touring", "Registration": "1 / 2007", "Mileage": "16,135 km", "Fuel type": "Gasoline", "Cubic capacity": "600 cc", "Power": "75 bhp", "Color": "Silver", "Previous owners": "1", "Modified": "1 day", "Times clicked": "990", "Short link": "www.car.gr/16560327", "Telephone": "None"}, "ad_seller": {}, "metadata": {"type": "Bikes", "brand": "Honda", "model": "CBF 600S"}, "extras": ["Alarm", "Bars", "Electric starter", "Engine Guards", "Four-stroke engine", "Gelatin", "Lights Xenon", "Sidestand", "Καρμπυρατέρ"], "description": "Η μοτοσυκλέτα διαθέτει πραγματικά χιλιόμετρα. 16135 - Δεν εχει χτυπήματα ούτε έχει πέσει ποτέ. Φυλάσσεται σε προστατευμένο χώρο, χωρίς να την επιρρεάζει η βροχή ή ο ήλιος. Γενικά είναι πολύ προσεγμένη. - Έχει φώτα XENON, μπάρες προστασίας κινητήρα,συναγερμό, προστατευτικό δέρμα ντεπόζιτου και μεγαλύτερη ζελατίνα. - Δύο κλειδιά καθώς και το βιβλίο χρήστη και σέρβις. - Την παρούσα στιγμή έχουν παραδωθεί οι πινακίδες και θα παρθούν πίσω μόνο σε σοβαρές προτάσεις. - Θα δωθούν μαζί δώρο και μία τσάντα ντεπόζιτου καθώς και πλαινά σαμάρια τα οποία φαίνονται σε κάποια απο τις φωτογραφίες. - Για επικοινωνία μαζι μου καλέστε παρακαλώ Σαββατοκύριακα όλη τη μέρα, ή τις καθημερινές μετά τις 7μμ εώς τις 9μμ. Δυστυχώς τις υπόλοιπες ώρες δεν μπορώ να ανταποκριθώ λόγω εργασίας. Στο δεύτερο νούμερο θα σας εξηπηρετησει ο πατέρας μου σε περίπτωση που δεν απαντήσω. - Δεν υπάρχει η δυνατότητα αποστολής της μηχανής και η τιμή δεν ειναι συζητήσιμη. - Less - "}