{"query": {"url": "https://www.car.gr/13679949-yamaha-tdm-900-tdm-900", "type": "CAR_ADDE", "trial_count": 1, "last_processed": 1553100712}, "title": "Yamaha TDM 900 TDM 900  '06", "ad_id": "13679949", "ad_data": {"Make/Model": "Yamaha TDM 900 TDM 900  '06", "Classified number": "13679949", "Price": "€3.700", "Category": "Bike - Sport Touring", "Registration": "5 / 2006", "Mileage": "70,000 km", "Fuel type": "Gasoline", "Cubic capacity": "900 cc", "Power": "92 bhp", "Color": "Black", "Kteo to": "05 / 2019", "Liters/100km": "5 (Εντός)", "Modified": "20 days", "Times clicked": "1072", "Short link": "www.car.gr/13679949", "Telephone": "None"}, "ad_seller": {}, "metadata": {"type": "Bikes", "brand": "Yamaha", "model": "TDM 900"}, "extras": ["Cargo Rack", "Electric starter", "Exchange with Moto accepted", "Lights Xenon", "Sidestand"], "description": "Η μοτοσυκλέτα είναι σε άριστη κατάσταση,δεκτός κάθε έλενχος. - Less - "}