{"query": {"url": "https://www.car.gr/20001811-bmw-f-650-gs-f-650-gs", "type": "CAR_ADDE", "trial_count": 1, "last_processed": 1553100091}, "title": "Bmw F 650 GS F 650 GS  '09", "ad_id": "20001811", "ad_data": {"Make/Model": "Bmw F 650 GS F 650 GS  '09", "Classified number": "20001811", "Price": "€5.800", "Category": "Bike - On/Off", "Registration": "12 / 2009", "Mileage": "38,000 km", "Fuel type": "Gasoline", "Cubic capacity": "798 cc", "Power": "78 bhp", "Color": "Silver (Metallic)", "Kteo to": "11 / 2020", "Liters/100km": "5 (Εντός)/4 (Μικτό)", "Previous owners": "1", "Modified": "16 days", "Times clicked": "368", "Short link": "www.car.gr/20001811", "Telephone": "None"}, "ad_seller": {}, "metadata": {"type": "Bikes", "brand": "Bmw", "model": "F 650 GS"}, "extras": ["ABS", "Bars", "Cargo Rack", "Catalyst", "Centerstand", "Engine Guards", "Gelatin", "Heated Handguards", "Injection", "Led lights", "Service Book", "Sidestand", "Skid Plate", "Top Box-Μπαγκαζιέρα", "Trip computer"], "description": "Μοτοσυκλέτα πάρα πολύ προσεγμένη ελάχιστα ίχνη φθοράς, με όλα τα Service της στην ώρα τους στον Παναγιωτόπουλο στον Γέρακα, διαθέτει πάρα πολλά extra όπως, ABS - Computer ταξιδίου - Led flash - πλήρες Σετ 3 βαλίτσες της BMW...προστατευτικά κάγκελα Motech - λασπωτήρες στον εμπρός και πίσω τροχό - Προβολείς ομίχλης εμπρός - χούφτες - θερμαινόμενες λαβές - κεντρικό Stand - Σέλα Comfort πολύ ξεκούραστη για ταξίδια - carbon όργανα - προστασία κάρτερ - καινούργια μπαταρία και λάστιχα - χρήση μόνο τα καλοκαίρια ...την παρκάρω σε κλειστό θερμαινόμενο γκαράζ τον χειμώνα....δεκτός οποιοσδήποτε έλεγχος σε εκδήλωση σοβαρού ενδιαφέροντος σε συνεργείο της επιλογής σας... υπάρχει αναλυτικό αρχείο και βιβλίο συντήρησης της αντιπροσωπείας....Παρακαλώ μόνο σοβαρά ενδιαφερόμενοι...περισσότερα από το τηλέφωνο...Ευχαριστώ πολύ - Less - "}