{"query": {"url": "https://www.car.gr/21476430-piaggio-liberty-125", "type": "CAR_ADDE", "trial_count": 1, "last_processed": 1553095321}, "title": "Piaggio Liberty 125  '09", "ad_id": "21476430", "ad_data": {"Make/Model": "Piaggio Liberty 125 '09", "Classified number": "21476430", "Price": "€900", "Category": "Bike - Roller/Scooter", "Registration": "1 / 2009", "Mileage": "17,500 km", "Fuel type": "Gasoline", "Cubic capacity": "125 cc", "Power": "10 bhp", "Color": "Orange", "Modified": "2 days", "Times clicked": "80", "Short link": "www.car.gr/21476430", "Telephone": "None"}, "ad_seller": {"Name": "GiannisR.", "Address": "ΜΑΡΚΟΠΟΥΛΟP.ΑΤΤΙΚΗΣ"}, "metadata": {"type": "Bikes", "brand": "Piaggio", "model": "Liberty 125"}, "extras": [], "description": "Σε άριστη κατάσταση πάρα πολύ λίγο δουλεμενο.δεκτος κάθε έλεγχος! - Less - "}