{"query": {"url": "https://www.car.gr/21114830-honda-xlr", "type": "CAR_ADDE", "trial_count": 1, "last_processed": 1553100684}, "title": "Honda XLR  '83", "ad_id": "21114830", "ad_data": {"Make/Model": "Honda XLR '83", "Classified number": "21114830", "Price": "€550", "Category": "Bike - Εnduro", "Registration": "1 / 1983", "Mileage": "63,000 km", "Fuel type": "Gasoline", "Cubic capacity": "250 cc", "Power": "18 bhp", "Color": "White", "Modified": "19 days", "Times clicked": "790", "Short link": "www.car.gr/21114830", "Telephone": "None"}, "ad_seller": {}, "metadata": {"type": "Bikes", "brand": "Honda", "model": "XLR"}, "extras": [], "description": "To mhxanaki 8elei mazemata (kaiei ladia,petaei ladia apo tn flatza tis kefalhs kai akougetai o piros pistoniou)gia afto h timh.. - Less - "}