{"query": {"url": "https://www.car.gr/13800226-piaggio-mp3-250", "type": "CAR_ADDE", "trial_count": 1, "last_processed": 1553104565}, "title": "Piaggio MP3 250  '07", "ad_id": "13800226", "ad_data": {"Make/Model": "Piaggio MP3 250 '07", "Classified number": "13800226", "Price": "€1.800", "Category": "Bike - Three Wheel", "Registration": "1 / 2007", "Mileage": "65,000 km", "Fuel type": "Gasoline", "Cubic capacity": "250 cc", "Power": "18 bhp", "Color": "Black", "Kteo to": "04 / 2020", "Modified": "49 days", "Times clicked": "1792", "Short link": "www.car.gr/13800226", "Telephone": "None"}, "ad_seller": {}, "metadata": {"type": "Bikes", "brand": "Piaggio", "model": "MP3 250"}, "extras": [], "description": "Σέρβις πριν 1 μήνα κτεο περασμενο Απρίλιο - Less - "}