{"query": {"url": "https://www.car.gr/5128486-honda-cb-650-cb-650f-14-honda", "type": "CAR_ADDE", "trial_count": 1, "last_processed": 1553094283}, "title": "Honda CB 650 CB 650F '14\"ΠΕΤΣΑΣ-HONDA\" '14", "ad_id": "5128486", "ad_data": {"Make/Model": "Honda CB 650 CB 650F '14\"ΠΕΤΣΑΣ-HONDA\" '14", "Classified number": "5128486", "Price": "€7.490", "Category": "Bike - Naked", "Registration": "12 / 2014", "Fuel type": "Gasoline", "Cubic capacity": "650 cc", "Power": "87 bhp", "Color": "Black", "Modified": "21 hours", "Times clicked": "9892", "Short link": "www.car.gr/5128486", "Telephone": "+30 2109582988"}, "ad_seller": {"Dealer": "ΥΙΟΙ ΓΙΑΝΝΗ ΠΕΤΣΑ Ο.Ε", "Address": "ΕΛ.ΒΕΝΙΖΕΛΟΥ242", "City": "ΚΑΛΛΙΘΕΑ", "": "+30 2109588004", "Fax": "+30 2109587256", "Dealer page": "https//petsas67.car.gr/", "Website": "http//www.motopetsas.com", "Open hours": "Δευτέρα έως Παρασκευή 0900 με 2030\nΣάββατο 0900 με 1430"}, "metadata": {"type": "Bikes", "brand": "Honda", "model": "CB 650"}, "extras": ["ABS", "Car Exchange", "Cast wheels", "Catalyst", "Credit card-Visa accepted", "Electric starter", "Exchange with Moto accepted", "Four-stroke engine", "Sidestand"], "description": "Προλάβετε ΠΡΟΣΦΟΡΑ \"ΠΕΤΣΑΣ\" για ένα τελευταίο σε ΜΑΥΡΟ ΜΑΤ!!!! - Από 8.070€ τώρα μόνο 7.490€!!!! - ΠΑΝΤΑ ΜΕ ΤΙΣ ΠΑΡΟΧΕΣ \"ΠΕΤΣΑΣ\". - ΕΓΓΥΗΣΗ ΕΠΙΣΗΜΗΣ ΑΝΤΙΠΡΟΣΩΠΕΙΑΣ!! - ΕΞΟΥΣΙΟΔΟΤΗΜΕΝΟ SERVICE ΜΕ EXTRA ΠΑΡΟΧΕΣ!!!! - ΠΕΤΣΑΣ....ΑΠΟ ΤΟ \"1964\" ΠΑΝΤΑ ΤΟ ΚΑΛΥΤΕΡΟ ΓΙΑ ΕΣΑΣ!!!ΚΑΘΕΤΗ ΜΟΝΑΔΑ HONDA-ΚΑΛΛΙΘΕΑΣ:ΕΚΘΕΣΗ ΜΟΤΟΣΥΚΛΕΤΩΝ-ΠΑΠΙΩΝ-SCOOTER ΚΑΙΝΟΥΡΓΙΩΝ ΚΑΙ ΜΕΤΑΧΕΙΡΙΣΜΕΝΩΝ,SERVICE,ΓΝΗΣΙΑ ΑΝΤΑΛΛΑΚΤΙΚΑ,ΑΝΤΑΛΛΑΓΕΣ. \"ΞΕΧΩΡΙΣΤΕΣ ΠΡΟΣΦΟΡΕΣ ΓΙΑ ΤΟΥΣ ΕΠΙΣΚΕΠΤΕΣ ΤΟΥ Car.gr\" ΕΛΑΤΕ ΑΠΟ ΚΟΝΤΑ ΚΑΙ ΡΩΤΗΣΤΕ ΜΑΣ ΓΙΑ ΤΙΣ ΠΡΟΣΦΟΡΕΣ ΜΑΣ!!!ΑΓΟΡΕΣ ΚΑΙ ΜΟΝΟ ΜΕ ΤΗΝ ΠΙΣΤΩΤΙΚΗ ΣΑΣ. - ΕΓΓΥΗΣΗ ΕΠΙΣΗΜΗΣ ΑΝΤΙΠΡΟΣΩΠΕΙΑΣ!! ΕΞΟΥΣΙΟΔΟΤΗΜΕΝΟ SERVICE ΜΕ ΔΩΡΟ ΤΗΝ ΕΡΓΑΣΙΑ ΣΤΗΝ ΠΡΩΤΗ ΚΑΙ ΣΤΗΝ ΔΕΥΤΕΡΗ ΕΠΙΣΚΕΨΗ!!!! - Less - "}