{"query": {"url": "https://www.car.gr/9857607-bmw-r-1150-r", "type": "CAR_ADDE", "trial_count": 1, "last_processed": 1553100297}, "title": "Bmw R 1150 R  '02", "ad_id": "9857607", "ad_data": {"Make/Model": "Bmw R 1150 R '02", "Classified number": "9857607", "Price": "€4.000", "Category": "Bike - Sport Touring", "Registration": "6 / 2002", "Mileage": "55,000 km", "Fuel type": "Gasoline", "Cubic capacity": "1,150 cc", "Power": "85 bhp", "Color": "Light Blue (Metallic)", "Kteo to": "06 / 2020", "Liters/100km": "5.7 (Εκτός)", "Modified": "17 days", "Times clicked": "683", "Short link": "www.car.gr/9857607", "Telephone": "None"}, "ad_seller": {}, "metadata": {"type": "Bikes", "brand": "Bmw", "model": "R 1150 R"}, "extras": [], "description": "ΥΠΕΡΑΡΙΣΤΗ ΚΑΤΑΣΤΑΣΗ! ΧΙΛΙΟΜΕΤΡΑ ΠΡΑΓΜΑΤΙΚΑ. ΔΕΚΤΟΣ ΚΑΘΕ ΕΛΕΓΧΟΣ. ΧΡΗΣΗ ΜΟΝΟΝ ΑΝΟΙΞΗ - ΚΑΛΟΚΑΙΡΙ. ΦΥΛΑΣΣΟΜΕΝΗ ΠΑΝΤΑ ΣΕ ΓΚΑΡΑΖ. 23 3 2017 ΤΟΠΟΘΕΤΗΣΗ ΝΕΑΣ ΜΠΑΤΑΡΙΑΣ. - 15/9/2017 ΤΟΠΟΘΕΤΗΣΗ ΝΕΩΝ ΕΛΑΣΤΙΚΩΝ BRIDGESTONE F 120/70/17 R 180/55/17 KM 45400 - Less - "}