{"query": {"url": "https://www.car.gr/15833488-ducati-monster-900", "type": "CAR_ADDE", "trial_count": 1, "last_processed": 1553096304}, "title": "Ducati Monster 900  '01", "ad_id": "15833488", "ad_data": {"Make/Model": "Ducati Monster 900 '01", "Classified number": "15833488", "Price": "€4.800", "Category": "Bike - Naked", "Registration": "1 / 2001", "Mileage": "15,000 km", "Fuel type": "Gasoline", "Cubic capacity": "900 cc", "Power": "80 bhp", "Color": "Yellow", "Modified": "5 days", "Times clicked": "635", "Short link": "www.car.gr/15833488", "Telephone": "+30 2221060438"}, "ad_seller": {"Dealer": "MIMIKOS MOTOSHOP KTM", "Address": "ΡΟΔΩΝ&Ε.ΟΧΑΛΚΙΔΑΣ-ΑΙΔΗΨΟΥ-ΧΑΛΚΙΔΑ", "City": "ΧΑΛΚΙΔΑ", "": "+30 2221060438", "Fax": "+30 2221060439", "Dealer page": "https//mmimikos.car.gr/"}, "metadata": {"type": "Bikes", "brand": "Ducati", "model": "Monster 900"}, "extras": [], "description": "ΣΕ ΑΡΙΣΤΗ ΚΑΤΑΣΤΑΣΗ ΜΕ ΠΟΛΛΑ EXTRA - ΓΙΑ ΠΕΡΙΣΣΟΤΕΡΕΣ ΠΛΗΡΟΦΟΡΙΕΣ ΕΠΙΚΟΙΝΩΝΗΣΤΕ ΜΕ ΤΟ 6949363344 (ΒΑΓΓΕΛΗΣ) - Ή ΜΕ ΤΟ SERVICE DUCATI ΦΙΛΛΙΠΑΚΗΣ - Less - "}