{"query": {"url": "https://www.car.gr/14588576-bmw-k-1200-s", "type": "CAR_ADDE", "trial_count": 1, "last_processed": 1553099164}, "title": "Bmw K 1200 S  '05", "ad_id": "14588576", "ad_data": {"Make/Model": "Bmw K 1200 S '05", "Classified number": "14588576", "Price": "€5.300", "Category": "Bike - Sport Touring", "Registration": "8 / 2005", "Mileage": "50,100 km", "Fuel type": "Gasoline", "Cubic capacity": "1,200 cc", "Power": "167 bhp", "Color": "Grey (Metallic)", "Previous owners": "1", "Modified": "13 days", "Times clicked": "213", "Short link": "www.car.gr/14588576", "Telephone": "None"}, "ad_seller": {"Name": "Απόστολος", "Address": "ΒΡΙΛΗΣΣΙΑP.ΑΤΤΙΚΗΣ"}, "metadata": {"type": "Bikes", "brand": "Bmw", "model": "K 1200 S"}, "extras": ["ABS", "Alarm", "Car Exchange", "Cargo Rack", "Cast wheels", "Catalyst", "Electric starter", "Exchange with Moto accepted", "Exhaust Special", "Four-stroke engine", "Gelatin", "Heated Handguards", "Remote Control", "Service Book", "Sidestand", "Skid Plate", "Trip computer"], "description": "ABS, esa (ηλεκτρική ανάρτηση), υπολογιστής ταξιδιού, θερμαινόμενα Grip και συναγερμός. όλα της μάνας του. Καινούργια ελαστικά Michelin. Περιλαμβάνει επιπλέων: λευκά φλας & πλατύ σταντ & μανιτάρια προστασίας & ζελατίνα & προστατευτικά φρένων & Cruise Control, όλα της Wunderlich, επίσης σχάρα της BMW και εξάτμιση της MIVV. Στην τιμή δίνονται και δύο πλαηνές μπαγαζιέρες και ένα ολοκαίνουργιο μεγάλο Tank Back της BMW. - Δεκτή η ανταλλαγή με ηλεκτροκίνητο ή υβριδικό μικρό αυτοκίνητο. - Less - "}